PyCTPM/__init__.py
PyCTPM/ctpm.py
PyCTPM/core/__init__.py
PyCTPM/core/config.py
PyCTPM/core/constants.py
PyCTPM/core/eqConstants.py
PyCTPM/core/errors.py
PyCTPM/core/info.py
PyCTPM/core/package.py
PyCTPM/core/store.py
PyCTPM/core/utilities.py
PyCTPM/database/__init__.py
PyCTPM/database/dataInfo.py
PyCTPM/database/data_general.csv
PyCTPM/database/data_heat_capacity_constant_pressure.csv
PyCTPM/database/data_thermal_conductivity.csv
PyCTPM/database/data_viscosity.csv
PyCTPM/docs/__init__.py
PyCTPM/docs/dThermo.py
PyCTPM/docs/dUtility.py
PyCTPM/docs/eos.py
PyCTPM/docs/eosCore.py
PyCTPM/docs/eosData.py
PyCTPM/docs/extCore.py
PyCTPM/docs/gasTransPor.py
PyCTPM/docs/prop.py
PyCTPM-1.0.6.dist-info/LICENSE.md
PyCTPM-1.0.6.dist-info/METADATA
PyCTPM-1.0.6.dist-info/WHEEL
PyCTPM-1.0.6.dist-info/top_level.txt
PyCTPM-1.0.6.dist-info/RECORD
